ide/README.md
ide/__init__.py
ide/agenthub/README.md
ide/agenthub/__init__.py
ide/agenthub/browsing_agent/README.md
ide/agenthub/browsing_agent/__init__.py
ide/agenthub/browsing_agent/browsing_agent.py
ide/agenthub/browsing_agent/response_parser.py
ide/agenthub/browsing_agent/utils.py
ide/agenthub/codeact_agent/README.md
ide/agenthub/codeact_agent/__init__.py
ide/agenthub/codeact_agent/codeact_agent.py
ide/agenthub/codeact_agent/function_calling.py
ide/agenthub/codeact_agent/prompts/additional_info.j2
ide/agenthub/codeact_agent/prompts/in_context_learning_example.j2
ide/agenthub/codeact_agent/prompts/in_context_learning_example_suffix.j2
ide/agenthub/codeact_agent/prompts/microagent_info.j2
ide/agenthub/codeact_agent/prompts/system_prompt.j2
ide/agenthub/codeact_agent/prompts/system_prompt_interactive.j2
ide/agenthub/codeact_agent/prompts/system_prompt_long_horizon.j2
ide/agenthub/codeact_agent/prompts/user_prompt.j2
ide/agenthub/codeact_agent/tools/__init__.py
ide/agenthub/codeact_agent/tools/bash.py
ide/agenthub/codeact_agent/tools/browser.py
ide/agenthub/codeact_agent/tools/condensation_request.py
ide/agenthub/codeact_agent/tools/finish.py
ide/agenthub/codeact_agent/tools/ipython.py
ide/agenthub/codeact_agent/tools/llm_based_edit.py
ide/agenthub/codeact_agent/tools/str_replace_editor.py
ide/agenthub/codeact_agent/tools/think.py
ide/agenthub/dummy_agent/__init__.py
ide/agenthub/dummy_agent/agent.py
ide/agenthub/loc_agent/README.md
ide/agenthub/loc_agent/__init__.py
ide/agenthub/loc_agent/function_calling.py
ide/agenthub/loc_agent/loc_agent.py
ide/agenthub/loc_agent/tools/__init__.py
ide/agenthub/loc_agent/tools/explore_structure.py
ide/agenthub/loc_agent/tools/search_content.py
ide/agenthub/readonly_agent/__init__.py
ide/agenthub/readonly_agent/function_calling.py
ide/agenthub/readonly_agent/prompts/additional_info.j2
ide/agenthub/readonly_agent/prompts/in_context_learning_example.j2
ide/agenthub/readonly_agent/prompts/in_context_learning_example_suffix.j2
hanzo_dev-1.22.0.dist-info/METADATA
hanzo_dev-1.22.0.dist-info/WHEEL
hanzo_dev-1.22.0.dist-info/entry_points.txt
hanzo_dev-1.22.0.dist-info/RECORD
